{
  "234119": "129084651.json",
  "conceptId": "173508724",
  "Primary Source": "898006288.json",
  "Secondary Source": "PPLHOUSE",
  "QuestID - radio button or multi-answer format questions questions.": "641651634.json",
  "Source Question": "People in house number",
  "Question Text": "People in house number",
  "Variable Label": "SrvBOH_PplHouse_v1r0",
  "Variable Name": "PPLHOUSE",
  "Connect Value for Select all that apply questions": "Num",
  "Variable Type": "2",
  "Old Quest Value": "N/A",
  "Connect Id Array": "No",
  "Required": "Yes",
  "@context": ""
}