{
  "234119": "129084651.json",
  "conceptId": "298689217",
  "Primary Source": "898006288.json",
  "Secondary Source": "HEARTATT",
  "QuestID - radio button or multi-answer format questions questions.": "624479779.json",
  "Source Question": "Heart attack (myocardial infarction) diagnosis year",
  "Question Text": "Heart attack (myocardial infarction) diagnosis year",
  "Variable Label": "SrvBOH_MIyear_v1r0",
  "Variable Name": "HEARTATT_YEAR",
  "Connect Value for Select all that apply questions": "Year",
  "Variable Type": "4",
  "Old Quest Value": "yyyy",
  "Connect Id Array": "No",
  "Required": "No",
  "PII": "Only display if MHGROUP1 = Heart attack",
  "@context": ""
}