{
  "conceptId": 380583570,
  "Primary Source": "129084651.json",
  "Secondary Source": "898006288.json",
  "QuestID - radio button or multi-answer format questions questions.": "771661245.json",
  "Source Question": "351657815.json",
  "Question Text": "Tunisian",
  "Variable Label": "Tunisian",
  "Variable Name": "SrvBOH_Tunisian_v1r0",
  "QuestID for check box or single answer questions. Also includes codes for radio button questions": 10,
  "Connect Value for Select all that apply questions": 9,
  "Variable Type": "Num",
  "Variable Length": 1,
  "Connect Value": [
    "104430631.json",
    "353358909.json"
  ],
  "Required": "No",
  "PII": "No",
  "Notes": "Only display if RACEETH = Middle Eastern or North African",
  "@context": ""
}