{
  "234119": "470640108.json",
  "Primary Source": "237817859.json",
  "Secondary Source": "Withdrawal",
  "Question Text": "Data destruction request signed",
  "Variable Label": "Signed data destruction request",
  "Variable Name": "HdWd_Datadestroysign_v1r0",
  "Variable Type": "Num",
  "Variable Length": "132198728.json",
  "Format/Value": [
    "No",
    "Yes"
  ],
  "Required": "Yes",
  "PII": "No",
  "Notes": "Set when form signed",
  "Dictionary": "Withdrawal, Study Manager Data Dictionary",
  "conceptId": "890870842.json",
  "@context": ""
}