{
  "234119": "129084651.json",
  "conceptId": "963867920",
  "Primary Source": "898006288.json",
  "Secondary Source": "WTLOSS2_4555",
  "QuestID - radio button or multi-answer format questions questions.": "431628922.json",
  "Source Question": "Other text box",
  "Question Text": "Other text box",
  "Variable Label": "SrvBOH_OtherWtLossDes4_v1r0",
  "Variable Name": "WTLOSS2_4555_TB",
  "Connect Value for Select all that apply questions": "Char",
  "Old Quest Value": "N/A",
  "Connect Id Array": "No",
  "Required": "No",
  "PII": "Only display if flag for percent weight change 45-55 = yes",
  "@context": ""
}