{
  "234119": "129084651.json",
  "conceptId": "985487786",
  "Primary Source": "898006288.json",
  "Secondary Source": "MOMCANC3F",
  "QuestID - radio button or multi-answer format questions questions.": "891925519.json",
  "Source Question": "Mom colon/rectal cancer age",
  "Question Text": "Mom colon/rectal cancer age",
  "Variable Label": "SrvBOH_MomColCancAge_v1r0",
  "Variable Name": "MOMCANC3F_AGE",
  "Connect Value for Select all that apply questions": "Num",
  "Variable Type": "2",
  "Old Quest Value": "N/A",
  "Connect Id Array": "No",
  "Required": "No",
  "PII": "Connect Format/Values - Only display if MOMCANC2= 5",
  "@context": ""
}